vault2vault.py
vault2vault-0.1.3.dist-info/LICENSE.md
vault2vault-0.1.3.dist-info/METADATA
vault2vault-0.1.3.dist-info/WHEEL
vault2vault-0.1.3.dist-info/entry_points.txt
vault2vault-0.1.3.dist-info/RECORD
