Metadata-Version: 2.1
Name: vault2vault
Version: 0.1.3
Summary: Recursively rekey ansible-vault encrypted files and in-line variables
Home-page: https://github.com/enpaul/vault2vault/
License: MIT
Keywords: ansible,vault,playbook,yaml,password
Author: Ethan Paul
Author-email: 24588726+enpaul@users.noreply.github.com
Requires-Python: >=3.7,<4.0
Classifier: Development Status :: 4 - Beta
Classifier: Environment :: Console
Classifier: Framework :: Ansible
Classifier: Intended Audience :: Developers
Classifier: Intended Audience :: Information Technology
Classifier: Intended Audience :: System Administrators
Classifier: License :: OSI Approved :: MIT License
Classifier: Natural Language :: English
Classifier: Operating System :: OS Independent
Classifier: Programming Language :: Python :: 3
Classifier: Programming Language :: Python :: 3.7
Classifier: Programming Language :: Python :: 3.8
Classifier: Programming Language :: Python :: 3.9
Classifier: Programming Language :: Python :: 3.10
Classifier: Programming Language :: Python :: 3.11
Classifier: Programming Language :: Python :: 3
Classifier: Programming Language :: Python :: 3.10
Classifier: Programming Language :: Python :: 3.11
Classifier: Programming Language :: Python :: 3.7
Classifier: Programming Language :: Python :: 3.8
Classifier: Programming Language :: Python :: 3.9
Classifier: Programming Language :: Python :: Implementation :: CPython
Provides-Extra: ansible
Requires-Dist: ansible-core (>=2.11.5,<3.0.0) ; extra == "ansible"
Requires-Dist: ruamel.yaml (>=0.17.16,<0.18.0)
Project-URL: Repository, https://github.com/enpaul/vault2vault/
